<?xml version="1.0" encoding="UTF-8"?><record_update>
    <sys_choice action="INSERT_OR_UPDATE" field="category" table="x_408970_safety_ap_x_408970_inspector_look_up" version="3">
        <sys_choice_set action="INSERT_OR_UPDATE">
            <element>category</element>
            <name>x_408970_safety_ap_x_408970_inspector_look_up</name>
            <sys_class_name>sys_choice_set</sys_class_name>
            <sys_created_by>admin</sys_created_by>
            <sys_created_on>2021-04-18 13:59:02</sys_created_on>
            <sys_id>5ad95612076be01072d9f7108c1ed0fd</sys_id>
            <sys_mod_count>0</sys_mod_count>
            <sys_name>category</sys_name>
            <sys_package display_value="Safety App" source="x_408970_safety_ap">8c234d9607afa01072d9f7108c1ed06d</sys_package>
            <sys_policy/>
            <sys_scope display_value="Safety App">8c234d9607afa01072d9f7108c1ed06d</sys_scope>
            <sys_update_name>sys_choice_x_408970_safety_ap_x_408970_inspector_look_up_category</sys_update_name>
            <sys_updated_by>admin</sys_updated_by>
            <sys_updated_on>2021-04-18 13:59:02</sys_updated_on>
        </sys_choice_set>
        <sys_choice action="INSERT_OR_UPDATE">
            <dependent_value/>
            <element>category</element>
            <hint/>
            <inactive>false</inactive>
            <label>-- New choice --</label>
            <language>en</language>
            <name>x_408970_safety_ap_x_408970_inspector_look_up</name>
            <sequence/>
            <synonyms/>
            <sys_created_by>admin</sys_created_by>
            <sys_created_on>2021-04-18 13:59:02</sys_created_on>
            <sys_domain>global</sys_domain>
            <sys_domain_path>/</sys_domain_path>
            <sys_id>5ed95612076be01072d9f7108c1ed0fc</sys_id>
            <sys_mod_count>0</sys_mod_count>
            <sys_updated_by>admin</sys_updated_by>
            <sys_updated_on>2021-04-18 13:59:02</sys_updated_on>
            <value>-- New choice --</value>
        </sys_choice>
    </sys_choice>
</record_update>
